<?xml version='1.0'?>
<card xmlns='http://sourceforge.net/projects/firemox'
	xmlns:xsi='http://www.w3.org/2001/XMLSchema-instance'
	xsi:schemaLocation='http://sourceforge.net/projects/firemox ../../validator.xsd'
	name="Niveous Wisps">
<rules-author-comment>riclas</rules-author-comment>

<!--
		w
	instant
	
	target creature becomes white until end of turn. tap that creature. draw a card.
 -->

	<init>
		<registers>
			<register index='white' value='1'/>
		</registers>
		<colors>white </colors>
		<idcards>instant </idcards>
		<properties> </properties>
	</init>
	<abilities>
		<activated-ability playable='this' name='' zone='hand'>
			<cost>
				<pay-mana value='manacost'/>
				<action ref="target-creature"/>
			</cost>
			<effects>
				<add-modifier>
					<color-modifier color="white" linked="false" operation="set">
				 		<until>
				 			<end-of-phase phase="cleanup"/>
				 		</until>
				 	</color-modifier>
				</add-modifier>
				<tap/>
				<target type='you'/>
				<action ref='draw-a-card'/>
				<action ref='finish-spell'/>
			</effects>
		</activated-ability>
	</abilities>
</card>
